coro_runner/__init__.py
coro_runner/enums.py
coro_runner/logging.py
coro_runner/runner.py
coro_runner/schema.py
coro_runner/test_runner.py
coro_runner/types.py
coro_runner/utils.py
coro_runner/backend/__init__.py
coro_runner/backend/base.py
coro_runner/backend/in_memory.py
coro_runner/backend/redis.py
coro_runner-0.2.7.dist-info/METADATA
coro_runner-0.2.7.dist-info/WHEEL
coro_runner-0.2.7.dist-info/top_level.txt
coro_runner-0.2.7.dist-info/RECORD
