Metadata-Version: 2.4
Name: coro-runner
Version: 0.2.7
Summary: It's a python based asyncio task schedular/queue mechanism
Requires-Python: >=3.11
Provides-Extra: mysql
Requires-Dist: aiomysql>=0.2.0; extra == "mysql"
Provides-Extra: pg
Requires-Dist: asyncpg>=0.29; extra == "pg"
Provides-Extra: redis
Requires-Dist: redis>=6.4; extra == "redis"
Requires-Dist: hiredis>=3.2; extra == "redis"
Provides-Extra: all
Requires-Dist: aiomysql>=0.2.0; extra == "all"
Requires-Dist: asyncpg>=0.29; extra == "all"
Requires-Dist: redis>=6.4; extra == "all"
Requires-Dist: hiredis>=3.2; extra == "all"
